jsonite/__init__.py
jsonite/javascript.py
jsonite/middleware.py
jsonite/provider.py
jsonite/transformer.py
JSONite-0.0.3.dist-info/LICENSE
JSONite-0.0.3.dist-info/METADATA
JSONite-0.0.3.dist-info/WHEEL
JSONite-0.0.3.dist-info/top_level.txt
JSONite-0.0.3.dist-info/RECORD
