Metadata-Version: 2.1
Name: JSONite
Version: 0.0.3
Summary: Python to Javascript variable converter for the Masonite framework.
Home-page: https://github.com/ChrisByrd14/JSONite
Author: Chris Byrd
Author-email: christopher.byrd2013@gmail.com
License: UNKNOWN
Platform: UNKNOWN
Classifier: Intended Audience :: Developers
Classifier: License :: OSI Approved :: MIT License
Classifier: Operating System :: OS Independent
Classifier: Programming Language :: Python :: 3 :: Only
Classifier: Natural Language :: English
Requires-Dist: masonite (>=2)
